pipcleaner/__init__.py
pipcleaner/main.py
pipcleaner-0.1.0.dist-info/METADATA
pipcleaner-0.1.0.dist-info/WHEEL
pipcleaner-0.1.0.dist-info/entry_points.txt
pipcleaner-0.1.0.dist-info/RECORD
