Metadata-Version: 2.1
Name: pipcleaner
Version: 0.1.0
Summary: Uninstall Python modules interactively
Author: Rog3rSm1th
Author-email: r0g3r5@protonmail.com
Requires-Python: >=3.9,<4.0
Classifier: Programming Language :: Python :: 3
Classifier: Programming Language :: Python :: 3.9
Classifier: Programming Language :: Python :: 3.10
Classifier: Programming Language :: Python :: 3.11
Requires-Dist: inquirer (>=3.1.4,<4.0.0)
